LICENSE
MANIFEST.in
README.md
setup.py
bosonic_jax/VERSION.txt
bosonic_jax/__init__.py
bosonic_jax.egg-info/PKG-INFO
bosonic_jax.egg-info/SOURCES.txt
bosonic_jax.egg-info/dependency_links.txt
bosonic_jax.egg-info/requires.txt
bosonic_jax.egg-info/top_level.txt
bosonic_jax/circuit/__init__.py
bosonic_jax/circuit/base.py
bosonic_jax/circuit/gates/__init__.py
bosonic_jax/circuit/gates/cavity.py
bosonic_jax/circuit/gates/cavity_qubit.py
bosonic_jax/circuit/gates/qubit.py
bosonic_jax/codes/__init__.py
bosonic_jax/codes/base.py
bosonic_jax/codes/binomial.py
bosonic_jax/codes/cat.py
bosonic_jax/codes/gkp.py
bosonic_jax/codes/mode.py
bosonic_jax/codes/qubit.py
bosonic_jax/simulator/__init__.py
bosonic_jax/simulator/base.py
docs/gen_ref_pages.py
docs/assets/logo_sq.png