Metadata-Version: 2.1
Name: bosonic-jax
Version: 0.1.0.1
Summary: Bosonic JAX
Home-page: https://github.com/EQuS/bosonic-jax
Author: Shantanu Jha, Shoumik Chowdhury, Max Hays
Author-email: shantanu.rajesh.jha@gmail.com
License: Apache 2.0
Project-URL: Bug Tracker, https://github.com/EQuS/bosonic-jax/issues
Project-URL: Documentation, https://equs.github.io/bosonic-jax
Project-URL: Source Code, https://github.com/EQuS/bosonic-jax
Project-URL: Tutorials, https://github.com/EQuS/bosonic-jax/tutorials
Project-URL: Tests, https://github.com/EQuS/bosonic-jax/test
Keywords: bosonic jax qubits cQED QEC GKP quantum error correction
Classifier: Environment :: Console
Classifier: License :: OSI Approved :: Apache Software License
Classifier: Intended Audience :: Developers
Classifier: Intended Audience :: Science/Research
Classifier: Operating System :: Microsoft :: Windows
Classifier: Operating System :: MacOS
Classifier: Operating System :: POSIX :: Linux
Classifier: Programming Language :: Python :: 3 :: Only
Classifier: Programming Language :: Python :: 3.8
Classifier: Programming Language :: Python :: 3.9
Classifier: Topic :: Scientific/Engineering
Requires-Python: >=3.7
License-File: LICENSE
Requires-Dist: numpy
Requires-Dist: scipy
Requires-Dist: matplotlib
Requires-Dist: qutip
Requires-Dist: tqdm
Requires-Dist: cython>=0.29.20
Requires-Dist: jax[cpu]
Provides-Extra: dev
Requires-Dist: jupyterlab>=3.1.0; extra == "dev"
Requires-Dist: mypy; extra == "dev"
Requires-Dist: pylint; extra == "dev"
Requires-Dist: black; extra == "dev"
Provides-Extra: docs
Requires-Dist: mkdocs; extra == "docs"
Requires-Dist: mkdocs-material; extra == "docs"
Requires-Dist: mkdocs-literate-nav; extra == "docs"
Requires-Dist: mkdocs-section-index; extra == "docs"
Requires-Dist: mkdocs-gen-files; extra == "docs"
Requires-Dist: mkdocstrings-python; extra == "docs"
